biocracker/__init__.py
biocracker/version.py
biocracker/data/AMP-binding_converted.hmm
biocracker/inference/__init__.py
biocracker/inference/base.py
biocracker/inference/model_paras.py
biocracker/inference/model_pfam.py
biocracker/inference/registry.py
biocracker/io/__init__.py
biocracker/io/gbk_antismash.py
biocracker/io/options.py
biocracker/io/readers.py
biocracker/model/__init__.py
biocracker/model/annotations.py
biocracker/model/domain.py
biocracker/model/gene.py
biocracker/model/inference.py
biocracker/model/region.py
biocracker/pipelines/__init__.py
biocracker/pipelines/annotate_region.py
biocracker/query/__init__.py
biocracker/query/modules.py
biocracker/utils/__init__.py
biocracker/utils/download.py
biocracker/utils/json.py
biocracker/utils/logging.py
biocracker-2.0.3.dist-info/METADATA
biocracker-2.0.3.dist-info/WHEEL
biocracker-2.0.3.dist-info/licenses/LICENSE
biocracker-2.0.3.dist-info/RECORD
