Metadata-Version: 2.4
Name: biocracker
Version: 2.0.3
Summary: BioCracker is a parser for antiSMASH output GenBank files
Project-URL: Homepage, https://github.com/moltools/biocracker
Project-URL: Repository, https://github.com/moltools/biocracker
Project-URL: Issues, https://github.com/moltools/biocracker/issues
Project-URL: Documentation, https://github.com/moltools/biocracker#readme
Author-email: David Meijer <david.meijer@wur.nl>
License-Expression: MIT
License-File: LICENSE
Keywords: antismash,parser
Classifier: Development Status :: 5 - Production/Stable
Classifier: Intended Audience :: Science/Research
Classifier: License :: OSI Approved :: MIT License
Classifier: Programming Language :: Python
Classifier: Programming Language :: Python :: 3
Classifier: Programming Language :: Python :: 3.10
Classifier: Programming Language :: Python :: 3.11
Classifier: Topic :: Scientific/Engineering :: Bio-Informatics
Requires-Python: <3.12,>=3.10
Requires-Dist: biopython
Requires-Dist: ijson
Requires-Dist: joblib
Requires-Dist: numpy==1.23.0
Requires-Dist: pyhmmer
Requires-Dist: scikit-learn==1.2.0
Requires-Dist: tqdm
Provides-Extra: dev
Requires-Dist: pytest; extra == 'dev'
Requires-Dist: ruff; extra == 'dev'
